{"type": "Feature", "id": 12514737, "geometry": {"type": "Point", "coordinates": [110.634201, 45.326401]}, "properties": {"woe:id": 12514737, "woe:parent_id": 2265458, "woe:name": "Boro Hoboriin Airport", "woe:placetype": 14, "woe:placetype_name": "Airport", "woe:lang": "ENG", "iso:country": "MN", "meta:provider": ["geoplanet:7.3.1", "geoplanet:7.3.2", "geoplanet:7.4.0", "geoplanet:7.4.1", "geoplanet:7.5.1", "geoplanet:7.5.2", "geoplanet:7.6.0", "geoplanet:7.8.1", "geoplanet:7.9.0", "geoplanet:7.10.0", "geoplanet:8.0.0", "woeplanet:8.0.0"], "meta:indexed": "2020-08-20T20:26:37.212338", "meta:updated": "2020-10-14T11:16:58.189180", "woe:hierarchy": {"continent": 24865671, "country": 23424887, "town": 0, "planet": 1, "county": 0, "suburb": 0, "state": 2346161, "region": 0, "localadmin": 0}, "woe:timezone_id": 28350862, "woe:hash": "y2n9ve3m7tx3", "woe:centroid": [110.634201, 45.326401], "geom:latitude": 45.326401, "geom:longitude": 110.634201, "geom:hash": "y2n9ve3m7tx3", "woe:latitude": 45.326401, "geom:centroid": [110.634201, 45.326401], "woe:longitude": 110.634201, "woe:repo": "woeplanet-airport-mn", "geom:area": 0.0, "woe:scale": 19}}